MANIFEST.in
README.md
requirements.txt
setup.cfg
setup.py
versioneer.py
botcity/plugins/gmail/__init__.py
botcity/plugins/gmail/_version.py
botcity/plugins/gmail/plugin.py
botcity/plugins/gmail/utils.py
botcity_gmail_plugin.egg-info/PKG-INFO
botcity_gmail_plugin.egg-info/SOURCES.txt
botcity_gmail_plugin.egg-info/dependency_links.txt
botcity_gmail_plugin.egg-info/requires.txt
botcity_gmail_plugin.egg-info/top_level.txt
tests/test_import.py
tests/test_plugin.py