Metadata-Version: 2.4
Name: botcity-gmail-plugin
Version: 0.2.6
Home-page: https://bitbucket.org/botcitydev/bot-gmail-plugin-python.git
Requires-Python: >=3.7
Requires-Dist: imap-tools>=1.11
Requires-Dist: google-api-python-client
Requires-Dist: google-auth-oauthlib
Requires-Dist: google-auth-httplib2
Dynamic: description
Dynamic: description-content-type
Dynamic: home-page
Dynamic: requires-dist
Dynamic: requires-python
